oomysql.py
oomysql-1.1.2.dist-info/LICENSE
oomysql-1.1.2.dist-info/WHEEL
oomysql-1.1.2.dist-info/METADATA
oomysql-1.1.2.dist-info/RECORD
